pandas_diff/__init__.py
pandas_diff/cli.py
pandas_diff/pandas_diff.py
pandas_diff/pre_process.py
pandas_diff/process_results.py
pandas_diff-1.3.0.dist-info/AUTHORS.rst
pandas_diff-1.3.0.dist-info/LICENSE
pandas_diff-1.3.0.dist-info/METADATA
pandas_diff-1.3.0.dist-info/WHEEL
pandas_diff-1.3.0.dist-info/entry_points.txt
pandas_diff-1.3.0.dist-info/top_level.txt
pandas_diff-1.3.0.dist-info/RECORD
