Metadata-Version: 2.1
Name: pandas-diff
Version: 1.3.0
Summary: Python utility to extract differences between two pandas dataframes.
Home-page: https://github.com/jaimevalero/pandas_diff
Author: Jaime Valero
Author-email: jaimevalero78@gmail.com
License: MIT license
Keywords: pandas_diff
Platform: UNKNOWN
Classifier: Development Status :: 2 - Pre-Alpha
Classifier: Intended Audience :: Developers
Classifier: License :: OSI Approved :: MIT License
Classifier: Natural Language :: English
Classifier: Programming Language :: Python :: 3
Classifier: Programming Language :: Python :: 3.6
Classifier: Programming Language :: Python :: 3.7
Classifier: Programming Language :: Python :: 3.8
Requires-Python: >=3.6
License-File: LICENSE
License-File: AUTHORS.rst
Requires-Dist: Click (>=7.0)
Requires-Dist: pandas
